<?xml version='1.0' encoding='utf-8'?>
<!DOCTYPE hibernate-configuration PUBLIC
        "-//Hibernate/Hibernate Configuration DTD 3.0//EN"
        "http://hibernate.sourceforge.net/hibernate-configuration-3.0.dtd">

<hibernate-configuration>
    <session-factory>
        <mapping class="dbService.dataSets.RequestDataSet"/>
        <mapping class="dbService.dataSets.StateDataSet"/>
        <mapping class="dbService.dataSets.ProjectDataSet"/>
        <mapping class="dbService.dataSets.UserDataSet"/>
        <mapping class="dbService.dataSets.PositionDataSet"/>
        <mapping class="dbService.dataSets.ProjectPositionDataSet"/>
        <mapping class="dbService.dataSets.PriorityDataSet"/>
        <mapping class="dbService.dataSets.TaskDataSet"/>
        <mapping class="dbService.dataSets.UserRoleDataset"/>
        <mapping class="dbService.dataSets.RoleDataSet"/>
    </session-factory>
</hibernate-configuration>